equation_tree/__init__.py
equation_tree/analysis.py
equation_tree/defaults.py
equation_tree/metrics.py
equation_tree/prior.py
equation_tree/sample.py
equation_tree/tree.py
equation_tree/data/_hashed_probabilities.json
equation_tree/src/__init__.py
equation_tree/src/sample_tree_structure.py
equation_tree/src/tree_node.py
equation_tree/util/__init__.py
equation_tree/util/conversions.py
equation_tree/util/io.py
equation_tree/util/priors.py
equation_tree/util/type_check.py
equation_tree-0.0.33.dist-info/LICENSE
equation_tree-0.0.33.dist-info/METADATA
equation_tree-0.0.33.dist-info/WHEEL
equation_tree-0.0.33.dist-info/top_level.txt
equation_tree-0.0.33.dist-info/RECORD
