Metadata-Version: 2.1
Name: equation_tree
Version: 0.0.33
Summary: Describe your contribution
Author-email: Younes Strittmatter <younes_strittmatter@brown.edu>
License: Copyright (c) 2023 Younes Strittmatter
Project-URL: homepage, http://www.empiricalresearch.ai
Project-URL: repository, https://github.com/AutoResearch/equation-tree
Project-URL: documentation, https://autoresearch.github.io/autora/
Requires-Python: <4,>=3.8
License-File: LICENSE
Requires-Dist: numpy
Requires-Dist: sympy
Requires-Dist: importlib-resources
Requires-Dist: tqdm
Requires-Dist: pandas
Requires-Dist: pyyaml
Provides-Extra: dev
Provides-Extra: docs
Requires-Dist: mkdocs-material ; extra == 'docs'
Requires-Dist: mkdocs-gen-files ; extra == 'docs'
Requires-Dist: mkdocs-literate-nav ; extra == 'docs'
Requires-Dist: mkdocs-section-index ; extra == 'docs'
Requires-Dist: mkdocs-multirepo-plugin ; extra == 'docs'
Requires-Dist: mkdocstrings-python ; extra == 'docs'
Requires-Dist: mkdocs-jupyter ; extra == 'docs'
Requires-Dist: pymdown-extensions ; extra == 'docs'
